quaterion/__init__.py
quaterion/dataset/__init__.py
quaterion/dataset/indexing_dataset.py
quaterion/dataset/label_cache_dataset.py
quaterion/dataset/similarity_data_loader.py
quaterion/dataset/similarity_dataset.py
quaterion/dataset/similarity_samples.py
quaterion/dataset/train_collator.py
quaterion/distances/__init__.py
quaterion/distances/base_distance.py
quaterion/distances/cosine.py
quaterion/distances/dot_product.py
quaterion/distances/euclidean.py
quaterion/distances/manhattan.py
quaterion/eval/__init__.py
quaterion/eval/accumulators/__init__.py
quaterion/eval/accumulators/accumulator.py
quaterion/eval/accumulators/group_accumulator.py
quaterion/eval/accumulators/pair_accumulator.py
quaterion/eval/attached_metric.py
quaterion/eval/base_metric.py
quaterion/eval/evaluator.py
quaterion/eval/group/__init__.py
quaterion/eval/group/group_metric.py
quaterion/eval/group/retrieval_r_precision.py
quaterion/eval/pair/__init__.py
quaterion/eval/pair/pair_metric.py
quaterion/eval/pair/retrieval_precision.py
quaterion/eval/pair/retrieval_reciprocal_rank.py
quaterion/eval/samplers/__init__.py
quaterion/eval/samplers/base_sampler.py
quaterion/eval/samplers/group_sampler.py
quaterion/eval/samplers/pair_sampler.py
quaterion/loss/__init__.py
quaterion/loss/arcface_loss.py
quaterion/loss/circle_loss.py
quaterion/loss/contrastive_loss.py
quaterion/loss/extras/__init__.py
quaterion/loss/extras/pytorch_metric_learning_wrapper.py
quaterion/loss/fast_ap_loss.py
quaterion/loss/group_loss.py
quaterion/loss/multiple_negatives_ranking_loss.py
quaterion/loss/online_contrastive_loss.py
quaterion/loss/pairwise_loss.py
quaterion/loss/similarity_loss.py
quaterion/loss/softmax_loss.py
quaterion/loss/triplet_loss.py
quaterion/main.py
quaterion/train/__init__.py
quaterion/train/cache/__init__.py
quaterion/train/cache/cache_config.py
quaterion/train/cache/cache_encoder.py
quaterion/train/cache/cache_model.py
quaterion/train/cache/cache_train_collator.py
quaterion-0.1.35.dist-info/LICENSE
quaterion-0.1.35.dist-info/METADATA
quaterion-0.1.35.dist-info/WHEEL
quaterion-0.1.35.dist-info/RECORD
