Metadata-Version: 2.1
Name: quaterion
Version: 0.1.35
Summary: Similarity Learning fine-tuning framework
Home-page: https://github.com/qdrant/quaterion
Keywords: framework,similarity-learning,metric-learning,similarity,deep-learning,pytorch
Author: Quaterion Authors
Author-email: team@quaterion.tech
Requires-Python: >=3.8,<3.11
Classifier: Programming Language :: Python :: 3
Classifier: Programming Language :: Python :: 3.8
Classifier: Programming Language :: Python :: 3.9
Classifier: Programming Language :: Python :: 3.10
Provides-Extra: full
Provides-Extra: pytorch-metric-learning
Requires-Dist: loguru (>=0.5.3,<0.6.0)
Requires-Dist: mmh3 (>=3.0.0,<4.0.0)
Requires-Dist: protobuf (>=3.9.2,<3.20)
Requires-Dist: pytorch-lightning (>=1.6.4,<2.0.0)
Requires-Dist: pytorch-metric-learning (>=1.3.0,<2.0.0) ; extra == "pytorch-metric-learning" or extra == "full"
Requires-Dist: quaterion-models (>=0.1.17,<0.2.0)
Requires-Dist: rich (>=12.4.4,<13.0.0)
Requires-Dist: torch (>=1.8.2)
Requires-Dist: torchmetrics (<=0.8.2)
Project-URL: Repository, https://github.com/qdrant/quaterion
